bstb/__init__.py
bstb/core.py
bstb/greatcircle.py
bstb/logo.py
bstb/loxodrome.py
bstb/word_value.py
bstb-0.2.4.dist-info/WHEEL
bstb-0.2.4.dist-info/METADATA
bstb-0.2.4.dist-info/licenses/LICENSE
bstb-0.2.4.dist-info/RECORD
