Metadata-Version: 2.1
Name: bstb
Version: 0.2.4
Summary: bstb - Geocaching toolbox
License: GPL-3.0
Author-email: Cees van de Griend <cees@griend.eu>
Requires-Python: >=3.9
Classifier: Development Status :: 4 - Beta
Classifier: License :: OSI Approved :: GNU General Public License v3 (GPLv3)
Classifier: Operating System :: OS Independent
Classifier: Programming Language :: Python :: 3
Classifier: Programming Language :: Python :: 3.10
Classifier: Programming Language :: Python :: 3.11
Classifier: Programming Language :: Python :: 3.9
Requires-Dist: drawsvg>=2.1.1
Project-URL: Documentation,  https://bstb.griend.eu/
Project-URL: Source, https://github.com/ceesvandegriend/bstb
